[
    {
        "id": "route_1000",
        "vehicle": "vehicle_1",
        "src_lat": 200,
        "src_lng": 400,
        "locations": [
            {
                "id": "Location_18",
                "lat": 27.838455859774875,
                "lng": 684.0487113967746
            },
            {
                "id": "Location_6",
                "lat": 24.23388979256271,
                "lng": 745.4095706982428
            },
            {
                "id": "Location_20",
                "lat": 15.189858505619808,
                "lng": 694.6946226372479
            },
            {
                "id": "Location_29",
                "lat": 132.88746858542032,
                "lng": 910.3120802939216
            },
            {
                "id": "Location_7",
                "lat": 126.67373520164205,
                "lng": 954.8423948341266
            },
            {
                "id": "Location_4",
                "lat": 258.8942748585621,
                "lng": 823.0446286226024
            },
            {
                "id": "Location_23",
                "lat": 263.8939104283667,
                "lng": 972.808684243321
            },
            {
                "id": "Location_1",
                "lat": 169.87093962876685,
                "lng": 904.6777242731478
            },
            {
                "id": "Location_14",
                "lat": 98.10213383678183,
                "lng": 880.0636263100253
            },
            {
                "id": "Location_12",
                "lat": 199.74493748337744,
                "lng": 963.7992077393517
            }
        ]
    },
    {
        "id": "route_1001",
        "vehicle": "vehicle_2",
        "src_lat": 200,
        "src_lng": 400,
        "locations": [
            {
                "id": "Location_9",
                "lat": 391.3800085377627,
                "lng": 561.2266531449283
            },
            {
                "id": "Location_30",
                "lat": 250.64585552112604,
                "lng": 724.8958883653079
            },
            {
                "id": "Location_24",
                "lat": 327.87179984884716,
                "lng": 655.874568460934
            },
            {
                "id": "Location_27",
                "lat": 256.8821392209857,
                "lng": 604.2911321463456
            },
            {
                "id": "Location_11",
                "lat": 159.511780995517,
                "lng": 572.4017857789453
            },
            {
                "id": "Location_5",
                "lat": 150.46129536116544,
                "lng": 550.2339212226578
            },
            {
                "id": "Location_13",
                "lat": 226.47123471266494,
                "lng": 632.3284004841632
            },
            {
                "id": "Location_3",
                "lat": 315.2854004897062,
                "lng": 601.1438958710877
            },
            {
                "id": "Location_21",
                "lat": 456.95285754908645,
                "lng": 520.8220774446843
            },
            {
                "id": "Location_17",
                "lat": 299.6141362984876,
                "lng": 714.5838915155714
            },
            {
                "id": "Location_10",
                "lat": 209.88899966298465,
                "lng": 627.6446856414998
            }
        ]
    },
    {
        "id": "route_1002",
        "vehicle": "vehicle_3",
        "src_lat": 200,
        "src_lng": 400,
        "locations": [
            {
                "id": "Location_28",
                "lat": 529.513009624648,
                "lng": 590.1338532411103
            },
            {
                "id": "Location_26",
                "lat": 450.6357768202923,
                "lng": 628.0502741574635
            },
            {
                "id": "Location_8",
                "lat": 381.8994107424348,
                "lng": 836.196375238548
            },
            {
                "id": "Location_16",
                "lat": 448.792850622471,
                "lng": 689.8275780033077
            },
            {
                "id": "Location_22",
                "lat": 484.32000475732553,
                "lng": 750.63121521121
            },
            {
                "id": "Location_25",
                "lat": 517.0924514021053,
                "lng": 733.6635794434474
            },
            {
                "id": "Location_15",
                "lat": 576.4223906737071,
                "lng": 812.9548132981919
            },
            {
                "id": "Location_2",
                "lat": 490.26173927453243,
                "lng": 974.085032159468
            },
            {
                "id": "Location_19",
                "lat": 558.9302670080083,
                "lng": 818.9937161438861
            }
        ]
    }
]